{"cameraMode":{"drawMode":0,"name":"Shaded","section":"Shading Mode"},"sceneLighting":true,"audioPlay":false,"sceneViewState":{"m_AlwaysRefresh":false,"showFog":true,"showSkybox":true,"showFlares":true,"showImageEffects":true,"showParticleSystems":true,"showVisualEffectGraphs":true,"m_FxEnabled":true},"in2DMode":false,"pivot":{"x":24.99126434326172,"y":-7.739192962646484,"z":-28.353078842163087},"rotation":{"x":-0.15150360763072968,"y":-0.6201796531677246,"z":0.12363769114017487,"w":-0.7597581744194031},"size":6.5331244468688969,"orthographic":false}